.gitignore
CODE_OF_CONDUCT.md
LICENSE
README.md
requirements.txt
setup.py
.github/workflows/build.yml
.github/workflows/release.yml
samourai_build_tools/build.py
samourai_build_tools/target_versions.py
samourai_build_tools.egg-info/PKG-INFO
samourai_build_tools.egg-info/SOURCES.txt
samourai_build_tools.egg-info/dependency_links.txt
samourai_build_tools.egg-info/entry_points.txt
samourai_build_tools.egg-info/not-zip-safe
samourai_build_tools.egg-info/requires.txt
samourai_build_tools.egg-info/top_level.txt
samourai_build_tools/scripts/build_bundles.py
samourai_build_tools/scripts/build_mpy_cross.py