Metadata-Version: 1.2
Name: samourai-build-tools
Version: 0.0.1b4
Summary: CircuitPython library build tools
Home-page: https://www.adafruit.com/
Author: Scott Shawcroft
Author-email: scott@adafruit.com
License: UNKNOWN
Platform: UNKNOWN
Requires-Python: >=3.7
